CHANGES.rst
LICENSE.txt
MANIFEST.in
README.rst
setup.py
tox.ini
src/pyaxl/__init__.py
src/pyaxl/axlhandler.py
src/pyaxl/axlsql.py
src/pyaxl/configuration.py
src/pyaxl/exceptions.py
src/pyaxl/utils.py
src/pyaxl.egg-info/PKG-INFO
src/pyaxl.egg-info/SOURCES.txt
src/pyaxl.egg-info/dependency_links.txt
src/pyaxl.egg-info/entry_points.txt
src/pyaxl.egg-info/not-zip-safe
src/pyaxl.egg-info/requires.txt
src/pyaxl.egg-info/top_level.txt
src/pyaxl/ccm/__init__.py
src/pyaxl/ccm/abstracts.py
src/pyaxl/ccm/common.py
src/pyaxl/ccm/mixings.py
src/pyaxl/ccm/xtypes.py
src/pyaxl/testing/__init__.py
src/pyaxl/testing/testing.py
src/pyaxl/testing/transport.py
src/pyaxl/testing/validate.py
src/pyaxl/testing/soap/10.5_user_armstrong_list.xml
src/pyaxl/testing/soap/10.5_user_riols_add.xml
src/pyaxl/testing/soap/10.5_user_riols_get.xml
src/pyaxl/testing/soap/10.5_user_riols_list.xml
src/pyaxl/testing/soap/10.5_user_riols_remove.xml
src/pyaxl/testing/soap/10.5_user_riols_update.xml
src/pyaxl/testing/soap/8.0_user_riols_get.xml