Metadata-Version: 1.1
Name: pyaxl
Version: 1.0
Summary: pyaxl is a python library accessing the Cisco Callmanger over the AXL interface
Home-page: https://github.com/bielbienne/pyaxl
Author: Samuel Riolo
Author-email: samuel.riolo@biel-bienne.ch
License: ZPL 2.1
Keywords: bielbienne cisco callmanger axl soap
Platform: UNKNOWN
Classifier: Programming Language :: Python :: 3 :: Only
Classifier: Natural Language :: English
Classifier: License :: OSI Approved :: Zope Public License
Classifier: Operating System :: OS Independent
Classifier: Development Status :: 4 - Beta
